chain_compose-0.0.1.dist-info/licenses/LICENSE
mindor/cli/__init__.py
mindor/cli/compose.py
chain_compose-0.0.1.dist-info/METADATA
chain_compose-0.0.1.dist-info/WHEEL
chain_compose-0.0.1.dist-info/entry_points.txt
chain_compose-0.0.1.dist-info/top_level.txt
chain_compose-0.0.1.dist-info/RECORD
