Metadata-Version: 2.4
Name: chain-compose
Version: 0.0.1
Summary: chain-compose: Declarative Blockchain and Workflow Orchestrator
Author-email: Hanyeol Cho <hanyeol.cho@gmail.com>
License-Expression: MIT
Project-URL: Homepage, https://github.com/hanyeol/model-compose
License-File: LICENSE
Requires-Dist: click
Requires-Dist: pyyaml
Requires-Dist: pydantic
Requires-Dist: python-dotenv
Requires-Dist: aiohttp
Requires-Dist: requests
Requires-Dist: fastapi
Requires-Dist: uvicorn
Requires-Dist: mcp>=1.10.1
Requires-Dist: ulid
Requires-Dist: gradio
Requires-Dist: Pillow
Requires-Dist: docker
Dynamic: license-file
